{
	"backtraceGraph" : 
	{
		"commands" : 
		[
			"install"
		],
		"files" : 
		[
			"CMakeLists.txt"
		],
		"nodes" : 
		[
			{
				"file" : 0
			},
			{
				"command" : 0,
				"file" : 0,
				"line" : 162,
				"parent" : 0
			},
			{
				"command" : 0,
				"file" : 0,
				"line" : 164,
				"parent" : 0
			},
			{
				"command" : 0,
				"file" : 0,
				"line" : 169,
				"parent" : 0
			},
			{
				"command" : 0,
				"file" : 0,
				"line" : 171,
				"parent" : 0
			},
			{
				"command" : 0,
				"file" : 0,
				"line" : 172,
				"parent" : 0
			},
			{
				"command" : 0,
				"file" : 0,
				"line" : 173,
				"parent" : 0
			},
			{
				"command" : 0,
				"file" : 0,
				"line" : 175,
				"parent" : 0
			},
			{
				"command" : 0,
				"file" : 0,
				"line" : 176,
				"parent" : 0
			},
			{
				"command" : 0,
				"file" : 0,
				"line" : 178,
				"parent" : 0
			},
			{
				"command" : 0,
				"file" : 0,
				"line" : 180,
				"parent" : 0
			},
			{
				"command" : 0,
				"file" : 0,
				"line" : 182,
				"parent" : 0
			},
			{
				"command" : 0,
				"file" : 0,
				"line" : 186,
				"parent" : 0
			},
			{
				"command" : 0,
				"file" : 0,
				"line" : 189,
				"parent" : 0
			},
			{
				"command" : 0,
				"file" : 0,
				"line" : 195,
				"parent" : 0
			},
			{
				"command" : 0,
				"file" : 0,
				"line" : 197,
				"parent" : 0
			},
			{
				"command" : 0,
				"file" : 0,
				"line" : 199,
				"parent" : 0
			},
			{
				"command" : 0,
				"file" : 0,
				"line" : 201,
				"parent" : 0
			},
			{
				"command" : 0,
				"file" : 0,
				"line" : 203,
				"parent" : 0
			},
			{
				"command" : 0,
				"file" : 0,
				"line" : 206,
				"parent" : 0
			}
		]
	},
	"installers" : 
	[
		{
			"backtrace" : 1,
			"component" : "Unspecified",
			"destination" : "lib",
			"isOptional" : true,
			"paths" : 
			[
				"extern/uriparser/liburiparserd.a"
			],
			"targetId" : "uriparser::@02988cca979bc22941f2",
			"targetIndex" : 99,
			"type" : "target"
		},
		{
			"backtrace" : 1,
			"component" : "Unspecified",
			"destination" : "include",
			"isOptional" : true,
			"paths" : 
			[
				"extern/uriparser/include/uriparser/UriBase.h",
				"extern/uriparser/include/uriparser/UriDefsAnsi.h",
				"extern/uriparser/include/uriparser/UriDefsConfig.h",
				"extern/uriparser/include/uriparser/UriDefsUnicode.h",
				"extern/uriparser/include/uriparser/Uri.h",
				"extern/uriparser/include/uriparser/UriIp4.h"
			],
			"type" : "file"
		},
		{
			"backtrace" : 2,
			"component" : "GLM",
			"destination" : "include",
			"paths" : 
			[
				"extern/glm/glm"
			],
			"type" : "directory"
		},
		{
			"backtrace" : 3,
			"component" : "Unspecified",
			"destination" : "lib",
			"paths" : 
			[
				"extern/libtinyxml2d.a"
			],
			"targetId" : "tinyxml2::@4b650f177ba80d6d5e76",
			"targetIndex" : 96,
			"type" : "target"
		},
		{
			"backtrace" : 4,
			"component" : "Unspecified",
			"destination" : "lib",
			"paths" : 
			[
				"extern/asyncplusplus/libasync++d.a"
			],
			"targetId" : "Async++::@be6564aa5c64527e2a11",
			"targetIndex" : 0,
			"type" : "target"
		},
		{
			"backtrace" : 5,
			"component" : "Unspecified",
			"destination" : "include",
			"paths" : 
			[
				"extern/asyncplusplus/include/async++.h"
			],
			"type" : "file"
		},
		{
			"backtrace" : 6,
			"component" : "Unspecified",
			"destination" : "include",
			"paths" : 
			[
				"extern/asyncplusplus/include/async++"
			],
			"type" : "directory"
		},
		{
			"backtrace" : 7,
			"component" : "Unspecified",
			"destination" : "lib",
			"paths" : 
			[
				"extern/spdlog/libspdlogd.a"
			],
			"targetId" : "spdlog::@2be8bbbfd43a5375bf0e",
			"targetIndex" : 94,
			"type" : "target"
		},
		{
			"backtrace" : 8,
			"component" : "Unspecified",
			"destination" : "include",
			"paths" : 
			[
				"extern/spdlog/include/spdlog"
			],
			"type" : "directory"
		},
		{
			"backtrace" : 9,
			"component" : "Unspecified",
			"destination" : "lib",
			"paths" : 
			[
				"extern/draco/libdracod.a"
			],
			"targetId" : "draco_static::@d4298ebd35d74cac9a3f",
			"targetIndex" : 76,
			"type" : "target"
		},
		{
			"backtrace" : 10,
			"component" : "Unspecified",
			"destination" : "lib",
			"paths" : 
			[
				"extern/sqlite3/libsqlite3d.a"
			],
			"targetId" : "sqlite3::@cf3f1bccc66fd96c99a5",
			"targetIndex" : 95,
			"type" : "target"
		},
		{
			"backtrace" : 11,
			"component" : "Unspecified",
			"destination" : "lib",
			"paths" : 
			[
				"extern/modp_b64/libmodp_b64d.a"
			],
			"targetId" : "modp_b64::@cef9afe0cfc566fe3f5d",
			"targetIndex" : 89,
			"type" : "target"
		},
		{
			"backtrace" : 12,
			"component" : "Unspecified",
			"destination" : "lib",
			"paths" : 
			[
				"extern/libcsprngd.a"
			],
			"targetId" : "csprng::@4b650f177ba80d6d5e76",
			"targetIndex" : 45,
			"type" : "target"
		},
		{
			"backtrace" : 13,
			"component" : "Unspecified",
			"destination" : "include",
			"paths" : 
			[
				"extern/GSL/include/gsl"
			],
			"type" : "directory"
		},
		{
			"backtrace" : 14,
			"component" : "Unspecified",
			"destination" : "lib",
			"paths" : 
			[
				"extern/KTX-Software/libktx_readd.a"
			],
			"targetId" : "ktx_read::@1f45bfcee8b52cae0b90",
			"targetIndex" : 82,
			"type" : "target"
		},
		{
			"backtrace" : 15,
			"component" : "Unspecified",
			"destination" : "lib",
			"paths" : 
			[
				"extern/libwebp/libwebpdecoderd.a"
			],
			"targetId" : "webpdecoder::@a0bd244d559eed9a0c1d",
			"targetIndex" : 102,
			"type" : "target"
		},
		{
			"backtrace" : 15,
			"component" : "Unspecified",
			"destination" : "include",
			"paths" : 
			[
				"extern/libwebp/src/webp/decode.h",
				"extern/libwebp/src/webp/types.h"
			],
			"type" : "file"
		},
		{
			"backtrace" : 16,
			"component" : "Unspecified",
			"destination" : "lib",
			"paths" : 
			[
				"cmake-build-debug/extern/libjpeg-turbo/lib/libturbojpegd.a"
			],
			"type" : "directory"
		},
		{
			"backtrace" : 17,
			"component" : "Unspecified",
			"destination" : "include",
			"paths" : 
			[
				"extern/rapidjson/include/rapidjson"
			],
			"type" : "directory"
		},
		{
			"backtrace" : 18,
			"component" : "Unspecified",
			"destination" : "lib",
			"paths" : 
			[
				"extern/libs2geometryd.a"
			],
			"targetId" : "s2geometry::@4b650f177ba80d6d5e76",
			"targetIndex" : 92,
			"type" : "target"
		},
		{
			"backtrace" : 19,
			"component" : "Unspecified",
			"destination" : "include",
			"paths" : 
			[
				"extern/expected-lite/include/nonstd"
			],
			"type" : "directory"
		}
	],
	"paths" : 
	{
		"build" : ".",
		"source" : "."
	}
}
